virtual_stories/VERSION
virtual_stories/__init__.py
virtual_stories/stories/automotive/after_sales_service/1_warranty_repair_request_en.txt
virtual_stories/stories/e_commerce/order_issues/1_delayed_delivery_enquiry_en.txt
virtual_stories/stories/education/emergency_support/1_system_crashed_exam_deadline_en.txt
virtual_stories/stories/entertainment_platform/product_inquiry/1_streaming_subscription_inquiry_en.txt
virtual_stories/stories/financial_services/loyalty_programs/1_credit_card_rewards_inquiry_en.txt
virtual_stories/stories/fitness_center/technical_support/1_app_login_issue_en.txt
virtual_stories/stories/healthcare/complaints_resolution/1_misdiagnosis_complaint_en.txt
virtual_stories/stories/public_utilities/feedback_suggestions/1_billing_system_improvement_en.txt
virtual_stories/stories/telecommunications/billing_payment/1_unexpected_charge_dispute_en.txt
virtual_stories/stories/travel_aviation/appointment_scheduling/1_flight_booking_change_en.txt
virtual_stories-0.2.0.dist-info/LICENSE
virtual_stories-0.2.0.dist-info/METADATA
virtual_stories-0.2.0.dist-info/WHEEL
virtual_stories-0.2.0.dist-info/RECORD
